slappy/__init__.py
slappy/helpers.py
slappy-0.5.1.dist-info/LICENSE.txt
slappy-0.5.1.dist-info/METADATA
slappy-0.5.1.dist-info/WHEEL
slappy-0.5.1.dist-info/top_level.txt
slappy-0.5.1.dist-info/RECORD
