Metadata-Version: 2.1
Name: slappy
Version: 0.5.1
Summary: Slack bot framework
Home-page: https://github.com/berekuk/slappy
Author: Vyacheslav Matyukhin
Author-email: me@berekuk.ru
License: MIT
Platform: UNKNOWN
Requires-Python: >=3.6
Requires-Dist: flask
Requires-Dist: apscheduler
Requires-Dist: slackclient
Requires-Dist: slackeventsapi (>=2.0.0)
